b.py-0.11.0.dist-info/RECORD
b.py-0.11.0.dist-info/METADATA
b.py-0.11.0.dist-info/metadata.json
b.py-0.11.0.dist-info/DESCRIPTION.rst
b.py-0.11.0.dist-info/WHEEL
b.py-0.11.0.data/scripts/b.py
bpy/__init__.py
bpy/api/asciidocapi.py
bpy/api/__init__.py
bpy/services/wordpress.py
bpy/services/__init__.py
bpy/services/blogger.py
bpy/services/base.py
bpy/handlers/html.py
bpy/handlers/text.py
bpy/handlers/rst.py
bpy/handlers/mkd.py
bpy/handlers/__init__.py
bpy/handlers/base.py
bpy/handlers/asciidoc.py
